omnidocs/__init__.py
omnidocs/_version.py
omnidocs/document.py
omnidocs/tasks/__init__.py
omnidocs/tasks/layout_extraction/__init__.py
omnidocs/tasks/layout_extraction/base.py
omnidocs/tasks/layout_extraction/doc_layout_yolo.py
omnidocs/tasks/layout_extraction/models.py
omnidocs/tasks/layout_extraction/rtdetr.py
omnidocs/tasks/layout_extraction/qwen/__init__.py
omnidocs/tasks/layout_extraction/qwen/api.py
omnidocs/tasks/layout_extraction/qwen/detector.py
omnidocs/tasks/layout_extraction/qwen/mlx.py
omnidocs/tasks/layout_extraction/qwen/pytorch.py
omnidocs/tasks/layout_extraction/qwen/vllm.py
omnidocs/tasks/ocr_extraction/__init__.py
omnidocs/tasks/ocr_extraction/base.py
omnidocs/tasks/ocr_extraction/easyocr.py
omnidocs/tasks/ocr_extraction/models.py
omnidocs/tasks/ocr_extraction/paddleocr.py
omnidocs/tasks/ocr_extraction/tesseract.py
omnidocs/tasks/text_extraction/__init__.py
omnidocs/tasks/text_extraction/base.py
omnidocs/tasks/text_extraction/models.py
omnidocs/tasks/text_extraction/dotsocr/__init__.py
omnidocs/tasks/text_extraction/dotsocr/api.py
omnidocs/tasks/text_extraction/dotsocr/extractor.py
omnidocs/tasks/text_extraction/dotsocr/pytorch.py
omnidocs/tasks/text_extraction/dotsocr/vllm.py
omnidocs/tasks/text_extraction/qwen/__init__.py
omnidocs/tasks/text_extraction/qwen/api.py
omnidocs/tasks/text_extraction/qwen/extractor.py
omnidocs/tasks/text_extraction/qwen/mlx.py
omnidocs/tasks/text_extraction/qwen/pytorch.py
omnidocs/tasks/text_extraction/qwen/vllm.py
omnidocs-0.2.5.dist-info/METADATA
omnidocs-0.2.5.dist-info/WHEEL
omnidocs-0.2.5.dist-info/licenses/LICENSE.md
omnidocs-0.2.5.dist-info/RECORD
