Metadata-Version: 2.4
Name: omnidocs
Version: 0.2.5
Summary: Unified Python toolkit for visual document processing - think Transformers for document AI
Project-URL: Homepage, https://github.com/adithya-s-k/OmniDocs
Project-URL: Documentation, https://adithya-s-k.github.io/OmniDocs/
Project-URL: Repository, https://github.com/adithya-s-k/OmniDocs
Project-URL: Issues, https://github.com/adithya-s-k/OmniDocs/issues
Project-URL: Changelog, https://github.com/adithya-s-k/OmniDocs/releases
Author-email: adithya-s-kolavi <adithyaskolavi@gmail.com>
License: Apache-2.0
License-File: LICENSE.md
Keywords: document-processing,layout-analysis,ocr,pdf,vision-language-models
Classifier: Development Status :: 3 - Alpha
Classifier: Intended Audience :: Developers
Classifier: Intended Audience :: Science/Research
Classifier: License :: OSI Approved :: Apache Software License
Classifier: Programming Language :: Python :: 3
Classifier: Programming Language :: Python :: 3.10
Classifier: Programming Language :: Python :: 3.11
Classifier: Programming Language :: Python :: 3.12
Classifier: Topic :: Scientific/Engineering :: Artificial Intelligence
Classifier: Topic :: Text Processing
Requires-Python: <3.13,>=3.10
Requires-Dist: doclayout-yolo>=0.0.4
Requires-Dist: huggingface-hub>=0.36.0
Requires-Dist: numpy>=2.2.6
Requires-Dist: pdfplumber>=0.11.9
Requires-Dist: pillow>=12.1.0
Requires-Dist: pydantic>=2.12.5
Requires-Dist: pypdfium2>=5.3.0
Requires-Dist: requests>=2.32.5
Requires-Dist: timm>=1.0.24
Requires-Dist: torch>=2.9.1
Requires-Dist: torchvision>=0.24.1
Requires-Dist: transformers>=4.57.6
Provides-Extra: all
Requires-Dist: accelerate>=1.0.0; extra == 'all'
Requires-Dist: openai>=1.0.0; extra == 'all'
Requires-Dist: qwen-vl-utils>=0.0.14; extra == 'all'
Requires-Dist: vllm>=0.6.0; extra == 'all'
Provides-Extra: api
Requires-Dist: openai>=1.0.0; extra == 'api'
Provides-Extra: mlx
Requires-Dist: mlx-vlm>=0.1.0; extra == 'mlx'
Requires-Dist: mlx>=0.20.0; extra == 'mlx'
Provides-Extra: pytorch
Requires-Dist: accelerate>=1.0.0; extra == 'pytorch'
Requires-Dist: qwen-vl-utils>=0.0.14; extra == 'pytorch'
Provides-Extra: vllm
Requires-Dist: accelerate>=1.0.0; extra == 'vllm'
Requires-Dist: qwen-vl-utils>=0.0.14; extra == 'vllm'
Requires-Dist: vllm>=0.6.0; extra == 'vllm'
